Metadata-Version: 1.1
Name: rh.osx
Version: 0.1.1
Summary: Python bindings to access native macOS APIs
Home-page: http://github.com/rharke/rh.osx
Author: Ranger Harke
Author-email: ranger.harke@gmail.com
License: MIT
Platform: UNKNOWN
Classifier: Development Status :: 3 - Alpha
Classifier: Environment :: MacOS X
Classifier: License :: OSI Approved :: MIT License
Classifier: Natural Language :: English
Classifier: Operating System :: MacOS :: MacOS X
Classifier: Programming Language :: Python
Classifier: Topic :: Software Development :: Libraries :: Python Modules
